fsak/__init__.py
fsak/fsak.py
fsak-0.1.2.dist-info/entry_points.txt
fsak-0.1.2.dist-info/WHEEL
fsak-0.1.2.dist-info/METADATA
fsak-0.1.2.dist-info/RECORD
