Metadata-Version: 2.1
Name: fsak
Version: 0.1.2
Summary: sak=swiss army knife
Author: fahadahammed
Author-email: iamfahadahammed@gmail.com
Requires-Python: >=3.6,<4.0
Classifier: Programming Language :: Python :: 3
Classifier: Programming Language :: Python :: 3.6
Classifier: Programming Language :: Python :: 3.7
Classifier: Programming Language :: Python :: 3.8
Classifier: Programming Language :: Python :: 3.9
